prodos/__init__.py
prodos/blocks.py
prodos/cli.py
prodos/device.py
prodos/directory.py
prodos/file.py
prodos/globals.py
prodos/metadata.py
prodos/p8datetime.py
prodos/volmap.py
prodos/volume.py
pyprodos-0.4.0.dist-info/licenses/LICENSE
pyprodos-0.4.0.dist-info/METADATA
pyprodos-0.4.0.dist-info/WHEEL
pyprodos-0.4.0.dist-info/entry_points.txt
pyprodos-0.4.0.dist-info/top_level.txt
pyprodos-0.4.0.dist-info/RECORD
