Metadata-Version: 2.4
Name: pyprodos
Version: 0.4.0
Summary: Python implementation of Apple ProDOS 8 file system
Author-email: Patrick Surry <patrick.surry@gmail.com>
Project-URL: Homepage, https://github.com/patricksurry/pyprodos
Project-URL: Issues, https://github.com/patricksurry/pyprodos/issues
Keywords: prodos,filesystem
Classifier: Programming Language :: Python :: 3
Classifier: License :: OSI Approved :: MIT License
Classifier: Operating System :: OS Independent
Requires-Python: >=3.11
License-File: LICENSE
Requires-Dist: bitarray>=3.7.1
Requires-Dist: rich>=13.0.0
Requires-Dist: typer>=0.19.2
Requires-Dist: typer-di>=0.1.3
Provides-Extra: dev
Requires-Dist: pytest>=8.4.2; extra == "dev"
Requires-Dist: pytest-cov>=6.0.0; extra == "dev"
Requires-Dist: pyright>=1.1.390; extra == "dev"
Requires-Dist: isort>=5.13.0; extra == "dev"
Dynamic: license-file
